redisvl/__init__.py
redisvl/exceptions.py
redisvl/types.py
redisvl/version.py
redisvl/cli/__init__.py
redisvl/cli/index.py
redisvl/cli/main.py
redisvl/cli/runner.py
redisvl/cli/stats.py
redisvl/cli/utils.py
redisvl/cli/version.py
redisvl/extensions/__init__.py
redisvl/extensions/constants.py
redisvl/extensions/cache/__init__.py
redisvl/extensions/cache/base.py
redisvl/extensions/cache/embeddings/__init__.py
redisvl/extensions/cache/embeddings/embeddings.py
redisvl/extensions/cache/embeddings/schema.py
redisvl/extensions/cache/llm/__init__.py
redisvl/extensions/cache/llm/base.py
redisvl/extensions/cache/llm/langcache.py
redisvl/extensions/cache/llm/schema.py
redisvl/extensions/cache/llm/semantic.py
redisvl/extensions/llmcache/__init__.py
redisvl/extensions/llmcache/base.py
redisvl/extensions/llmcache/schema.py
redisvl/extensions/llmcache/semantic.py
redisvl/extensions/message_history/__init__.py
redisvl/extensions/message_history/base_history.py
redisvl/extensions/message_history/message_history.py
redisvl/extensions/message_history/schema.py
redisvl/extensions/message_history/semantic_history.py
redisvl/extensions/router/__init__.py
redisvl/extensions/router/schema.py
redisvl/extensions/router/semantic.py
redisvl/extensions/session_manager/__init__.py
redisvl/extensions/session_manager/base_session.py
redisvl/extensions/session_manager/schema.py
redisvl/extensions/session_manager/semantic_session.py
redisvl/extensions/session_manager/standard_session.py
redisvl/index/__init__.py
redisvl/index/index.py
redisvl/index/storage.py
redisvl/query/__init__.py
redisvl/query/aggregate.py
redisvl/query/filter.py
redisvl/query/hybrid.py
redisvl/query/query.py
redisvl/redis/__init__.py
redisvl/redis/connection.py
redisvl/redis/constants.py
redisvl/redis/utils.py
redisvl/schema/__init__.py
redisvl/schema/fields.py
redisvl/schema/schema.py
redisvl/schema/type_utils.py
redisvl/schema/validation.py
redisvl/utils/__init__.py
redisvl/utils/compression.py
redisvl-0.13.0.dist-info/METADATA
redisvl-0.13.0.dist-info/WHEEL
redisvl-0.13.0.dist-info/entry_points.txt
redisvl-0.13.0.dist-info/licenses/LICENSE
redisvl-0.13.0.dist-info/RECORD
