Metadata-Version: 2.4
Name: redisvl
Version: 0.13.0
Summary: Python client library and CLI for using Redis as a vector database
Project-URL: Homepage, https://github.com/redis/redis-vl-python
Project-URL: Repository, https://github.com/redis/redis-vl-python
Project-URL: Documentation, https://docs.redisvl.com
Author-email: "Redis Inc." <applied.ai@redis.com>
License-Expression: MIT
License-File: LICENSE
Keywords: ai,redis,redis-client,vector-database,vector-search
Classifier: License :: OSI Approved :: MIT License
Classifier: Programming Language :: Python :: 3.9
Classifier: Programming Language :: Python :: 3.10
Classifier: Programming Language :: Python :: 3.11
Classifier: Programming Language :: Python :: 3.12
Classifier: Programming Language :: Python :: 3.13
Requires-Python: <3.14,>=3.9.2
Requires-Dist: jsonpath-ng>=1.5.0
Requires-Dist: ml-dtypes<1.0.0,>=0.4.0
Requires-Dist: numpy<3,>=1.26.0
Requires-Dist: pydantic<3,>=2
Requires-Dist: python-ulid>=3.0.0
Requires-Dist: pyyaml<7.0,>=5.4
Requires-Dist: redis<7.2,>=5.0
Requires-Dist: tenacity>=8.2.2
Provides-Extra: bedrock
Requires-Dist: boto3<2,>=1.36.0; extra == 'bedrock'
Requires-Dist: urllib3<2.2.0; extra == 'bedrock'
Provides-Extra: cohere
Requires-Dist: cohere>=4.44; extra == 'cohere'
Provides-Extra: langcache
Requires-Dist: langcache>=0.11.0; extra == 'langcache'
Provides-Extra: mistralai
Requires-Dist: mistralai>=1.0.0; extra == 'mistralai'
Provides-Extra: nltk
Requires-Dist: nltk<4,>=3.8.1; extra == 'nltk'
Provides-Extra: openai
Requires-Dist: openai>=1.1.0; extra == 'openai'
Provides-Extra: pillow
Requires-Dist: pillow>=11.3.0; extra == 'pillow'
Provides-Extra: sentence-transformers
Requires-Dist: sentence-transformers<4,>=3.4.0; extra == 'sentence-transformers'
Provides-Extra: vertexai
Requires-Dist: google-cloud-aiplatform<2.0.0,>=1.26; extra == 'vertexai'
Requires-Dist: protobuf<6.0.0,>=5.28.0; extra == 'vertexai'
Provides-Extra: voyageai
Requires-Dist: voyageai>=0.2.2; extra == 'voyageai'
